coco_assistant/__init__.py
coco_assistant/coco_assistant.py
coco_assistant/coco_stats.py
coco_assistant/coco_visualiser.py
coco_assistant/utils/__init__.py
coco_assistant/utils/anchors.py
coco_assistant/utils/det2seg.py
coco_assistant/utils/misc.py
coco_assistant/utils/remapper.py
coco_assistant-0.4.0.dist-info/entry_points.txt
coco_assistant-0.4.0.dist-info/LICENSE
coco_assistant-0.4.0.dist-info/WHEEL
coco_assistant-0.4.0.dist-info/METADATA
coco_assistant-0.4.0.dist-info/RECORD
