Metadata-Version: 2.1
Name: coco-assistant
Version: 0.4.0
Summary: Helper for dealing with MS-COCO annotations.
Home-page: https://github.com/ashnair1/coco_assistant
License: MIT
Author: Ashwin Nair
Author-email: ashnair0007@gmail.com
Requires-Python: >=3.7.1,<4.0
Classifier: Intended Audience :: Developers
Classifier: License :: OSI Approved :: MIT License
Classifier: Natural Language :: English
Classifier: Programming Language :: Python :: 3
Classifier: Programming Language :: Python :: 3.7
Classifier: Programming Language :: Python :: 3.8
Classifier: Programming Language :: Python :: 3.9
Provides-Extra: dev
Provides-Extra: doc
Provides-Extra: test
Requires-Dist: black (==20.8b1); extra == "test"
Requires-Dist: coco-ash (>=2.0.2,<3.0.0)
Requires-Dist: coverage (>=5.5,<6.0); extra == "test"
Requires-Dist: flake8 (==3.8.4); extra == "test"
Requires-Dist: flake8-docstrings (>=1.6.0,<2.0.0); extra == "test"
Requires-Dist: isort (==5.6.4); extra == "test"
Requires-Dist: livereload[doc] (>=2.6.3,<3.0.0); extra == "doc"
Requires-Dist: matplotlib (>=3.4.2,<4.0.0)
Requires-Dist: mkdocs (>=1.1.2,<2.0.0); extra == "doc"
Requires-Dist: mkdocs-autorefs (==0.1.1); extra == "doc"
Requires-Dist: mkdocs-gen-files[doc] (>=0.3.3,<0.4.0); extra == "doc"
Requires-Dist: mkdocs-include-markdown-plugin (>=1.0.0,<2.0.0); extra == "doc"
Requires-Dist: mkdocs-literate-nav[doc] (>=0.4.0,<0.5.0); extra == "doc"
Requires-Dist: mkdocs-material (>=7.1.0,<8.0.0); extra == "doc"
Requires-Dist: mkdocs-material-extensions (>=1.0.1,<2.0.0)
Requires-Dist: mkdocs-section-index[doc] (>=0.3.1,<0.4.0); extra == "doc"
Requires-Dist: mkdocstrings (>=0.13.6,<0.14.0); extra == "doc"
Requires-Dist: pandas (>=1.3.1,<2.0.0)
Requires-Dist: pip (>=20.3.1,<21.0.0); extra == "dev"
Requires-Dist: pre-commit (>=2.12.0,<3.0.0); extra == "dev"
Requires-Dist: pytest (>=6.2.0,<7.0.0); extra == "test"
Requires-Dist: pytest-cov (>=2.10.1,<3.0.0); extra == "test"
Requires-Dist: requests (>=2.26.0,<3.0.0)
Requires-Dist: seaborn (>=0.11.1,<0.12.0)
Requires-Dist: toml (>=0.10.2,<0.11.0); extra == "dev"
Requires-Dist: tox (>=3.20.1,<4.0.0); extra == "dev"
Requires-Dist: tqdm (>=4.62.0,<5.0.0)
Requires-Dist: twine (>=3.3.0,<4.0.0); extra == "dev"
Requires-Dist: virtualenv (>=20.2.2,<21.0.0); extra == "dev"
